{
  "Absol": {"level": 88, "abilities": {"Pressure": 1}, "items": {"Leftovers": 1}, "moves": {"Hidden Power Fighting": 1, "Shadow Ball": 1, "Swords Dance": 1, "Baton Pass": 0.8988, "Quick Attack": 0.1012}, "ivs": {"def": 30, "spa": 30, "spd": 30, "spe": 30}},
  "Aerodactyl": {"level": 76, "abilities": {"Pressure": 0.7994, "Rock Head": 0.2006}, "items": {"Liechi Berry": 0.7994, "Choice Band": 0.2006}, "moves": {"Earthquake": 1, "Hidden Power Flying": 1, "Rock Slide": 1, "Substitute": 0.7994, "Double-Edge": 0.2006}, "ivs": {"hp": 30, "atk": 30, "def": 30, "spa": 30, "spd": 30}},
  "Aggron": {"level": 84, "abilities": {"Rock Head": 1}, "items": {"Leftovers": 0.9053, "Choice Band": 0.0947}, "moves": {"Rock Slide": 1, "Iron Tail": 0.7282, "Substitute": 0.7082, "Earthquake": 0.491, "Toxic": 0.3849, "Thunder Wave": 0.3119, "Focus Punch": 0.3083, "Double-Edge": 0.0676}},
  "Aipom": {"level": 91, "abilities": {"Run Away": 0.5188, "Pickup": 0.4812}, "items": {"Leftovers": 1}, "moves": {"Double-Edge": 1, "Substitute": 1, "Shadow Ball": 0.5933, "Thunder Wave": 0.5779, "Baton Pass": 0.4903, "Focus Punch": 0.3385}},
  "Alakazam": {"level": 79, "abilities": {"Synchronize": 1}, "items": {"Leftovers": 1}, "moves": {"Psychic": 1, "Recover": 1, "Substitute": 0.493, "Fire Punch": 0.4219, "Ice Punch": 0.3848, "Calm Mind": 0.3741, "Encore": 0.3263}, "evs": {"atk": 0}, "ivs": {"atk": 0}},
  "Altaria": {"level": 85, "abilities": {"Natural Cure": 1}, "items": {"Leftovers": 1}, "moves": {"Dragon Claw": 1, "Hidden Power Flying": 0.7467, "Rest": 0.6929, "Earthquake": 0.3071, "Toxic": 0.2989, "Haze": 0.2929, "Flamethrower": 0.2555, "Fire Blast": 0.2551, "Dragon Dance": 0.151}},
  "Ampharos": {"level": 83, "abilities": {"Static": 1}, "items": {"Leftovers": 1}, "moves": {"Thunderbolt": 1, "Toxic": 0.722, "Fire Punch": 0.7153, "Heal Bell": 0.6751, "Hidden Power Grass": 0.4612, "Hidden Power Ice": 0.4264}, "evs": {"atk": 0}},
  "Arbok": {"level": 87, "abilities": {"Intimidate": 1}, "items": {"Leftovers": 0.7884, "Chesto Berry": 0.1081, "Choice Band": 0.1035}, "moves": {"Sludge Bomb": 1, "Rest": 0.5805, "Rock Slide": 0.5571, "Earthquake": 0.5531, "Hidden Power Fire": 0.5458, "Sleep Talk": 0.4724, "Double-Edge": 0.2911}},
  "Arcanine": {"level": 81, "abilities": {"Intimidate": 0.6582, "Flash Fire": 0.3418}, "items": {"Leftovers": 0.8569, "Chesto Berry": 0.1431}, "moves": {"Hidden Power Grass": 0.7686, "Toxic": 0.7097, "Flamethrower": 0.7084, "Rest": 0.6358, "Sleep Talk": 0.4927, "Extreme Speed": 0.3729, "Fire Blast": 0.3119}},
  "Ariados": {"level": 93, "abilities": {"Insomnia": 0.681, "Swarm": 0.319}, "items": {"Leftovers": 1}, "moves": {"Sludge Bomb": 0.9297, "Signal Beam": 0.9275, "Baton Pass": 0.8902, "Agility": 0.7641, "Spider Web": 0.2471, "Toxic": 0.2414}},
  "Armaldo": {"level": 82, "abilities": {"Battle Armor": 1}, "items": {"Leftovers": 0.8071, "Choice Band": 0.1929}, "moves": {"Earthquake": 1, "Hidden Power Bug": 1, "Rock Slide": 1, "Swords Dance": 0.8071, "Double-Edge": 0.1929}, "ivs": {"atk": 30, "def": 30, "spd": 30}},
  "Articuno": {"level": 82, "abilities": {"Pressure": 1}, "items": {"Leftovers": 0.7269, "Chesto Berry": 0.2731}, "moves": {"Ice Beam": 1, "Hidden Power Fire": 0.6969, "Toxic": 0.6061, "Rest": 0.5619, "Roar": 0.3115, "Sleep Talk": 0.2888, "Heal Bell": 0.2698, "Protect": 0.265}, "evs": {"atk": 0}},
  "Azumarill": {"level": 86, "abilities": {"Huge Power": 1}, "items": {"Leftovers": 0.753, "Choice Band": 0.247}, "moves": {"Hydro Pump": 1, "Hidden Power Ghost": 0.7563, "Encore": 0.753, "Return": 0.7501, "Brick Break": 0.7406}},
  "Banette": {"level": 88, "abilities": {"Insomnia": 1}, "items": {"Leftovers": 0.5363, "Salac Berry": 0.4637}, "moves": {"Shadow Ball": 1, "Destiny Bond": 0.7011, "Knock Off": 0.6167, "Will-O-Wisp": 0.6126, "Hidden Power Fighting": 0.606, "Endure": 0.4637}},
  "Beautifly": {"level": 100, "abilities": {"Swarm": 1}, "items": {"Leftovers": 1}, "moves": {"Morning Sun": 1, "Substitute": 1, "Toxic": 0.5425, "Hidden Power Bug": 0.5009, "Hidden Power Flying": 0.4991, "Stun Spore": 0.4575}, "ivs": {"atk": 30, "def": 30, "spd": 30}},
  "Beedrill": {"level": 91, "abilities": {"Swarm": 1}, "items": {"Salac Berry": 0.939, "Choice Band": 0.061}, "moves": {"Sludge Bomb": 1, "Hidden Power Bug": 0.8208, "Swords Dance": 0.7879, "Brick Break": 0.7075, "Endure": 0.6229, "Double-Edge": 0.061}},
  "Bellossom": {"level": 88, "abilities": {"Chlorophyll": 1}, "items": {"Leftovers": 1}, "moves": {"Hidden Power Grass": 1, "Moonlight": 0.6989, "Stun Spore": 0.5886, "Leech Seed": 0.5861, "Sludge Bomb": 0.567, "Sleep Powder": 0.5594}, "ivs": {"spa": 30}},
  "Blastoise": {"level": 83, "abilities": {"Torrent": 1}, "items": {"Leftovers": 0.759, "Chesto Berry": 0.241}, "moves": {"Surf": 1, "Ice Beam": 0.6347, "Earthquake": 0.6245, "Rest": 0.5328, "Toxic": 0.4905, "Sleep Talk": 0.2918, "Roar": 0.2848, "Mirror Coat": 0.141}},
  "Blaziken": {"level": 82, "abilities": {"Blaze": 1}, "items": {"Salac Berry": 0.7403, "Leftovers": 0.2597}, "moves": {"Fire Blast": 1, "Sky Uppercut": 0.8868, "Rock Slide": 0.5411, "Endure": 0.4207, "Thunder Punch": 0.3246, "Swords Dance": 0.3196, "Hidden Power Ice": 0.2986, "Reversal": 0.2087}},
  "Blissey": {"level": 78, "abilities": {"Natural Cure": 1}, "items": {"Leftovers": 1}, "moves": {"Soft-Boiled": 1, "Ice Beam": 0.706, "Thunderbolt": 0.4746, "Seismic Toss": 0.4733, "Thunder Wave": 0.4288, "Toxic": 0.4284, "Aromatherapy": 0.4015, "Calm Mind": 0.0874}, "evs": {"atk": 0}, "ivs": {"atk": 0}},
  "Breloom": {"level": 84, "abilities": {"Effect Spore": 1}, "items": {"Leftovers": 1}, "moves": {"Sky Uppercut": 0.7538, "Substitute": 0.7174, "Spore": 0.635, "Hidden Power Ghost": 0.404, "Hidden Power Rock": 0.4035, "Swords Dance": 0.36, "Leech Seed": 0.2579, "Focus Punch": 0.2424, "Mach Punch": 0.2259}},
  "Butterfree": {"level": 94, "abilities": {"Compound Eyes": 1}, "items": {"Leftovers": 1}, "moves": {"Psychic": 1, "Morning Sun": 0.7373, "Hidden Power Fire": 0.6904, "Sleep Powder": 0.6009, "Toxic": 0.5234, "Stun Spore": 0.3278, "Giga Drain": 0.1202}, "evs": {"atk": 0}},
  "Cacturne": {"level": 92, "abilities": {"Sand Veil": 1}, "items": {"Leftovers": 0.8089, "Petaya Berry": 0.1911}, "moves": {"Needle Arm": 1, "Hidden Power Dark": 0.7518, "Substitute": 0.7312, "Thunder Punch": 0.5269, "Leech Seed": 0.5122, "Focus Punch": 0.2848, "Spikes": 0.1931}},
  "Camerupt": {"level": 85, "abilities": {"Magma Armor": 1}, "items": {"Leftovers": 0.7545, "Choice Band": 0.1269, "Chesto Berry": 0.1186}, "moves": {"Earthquake": 1, "Fire Blast": 1, "Rest": 0.5887, "Sleep Talk": 0.4701, "Rock Slide": 0.3495, "Toxic": 0.3341, "Explosion": 0.2577}},
  "Castform": {"level": 90, "abilities": {"Forecast": 1}, "items": {"Leftovers": 1}, "moves": {"Return": 1, "Substitute": 0.688, "Ice Beam": 0.5839, "Thunder Wave": 0.5834, "Thunderbolt": 0.5793, "Flamethrower": 0.5655}},
  "Celebi": {"level": 75, "abilities": {"Natural Cure": 1}, "items": {"Leftovers": 1}, "moves": {"Psychic": 0.8927, "Recover": 0.8358, "Hidden Power Grass": 0.8224, "Calm Mind": 0.6329, "Baton Pass": 0.4115, "Heal Bell": 0.2029, "Leech Seed": 0.2019}, "evs": {"atk": 0}},
  "Charizard": {"level": 80, "abilities": {"Blaze": 1}, "items": {"Lum Berry": 0.3771, "Salac Berry": 0.3345, "Leftovers": 0.2884}, "moves": {"Fire Blast": 1, "Hidden Power Flying": 1, "Earthquake": 0.856, "Substitute": 0.4325, "Dragon Dance": 0.3771, "Belly Drum": 0.3345}, "ivs": {"hp": 30, "atk": 30, "def": 30, "spa": 30, "spd": 30}},
  "Chimecho": {"level": 88, "abilities": {"Levitate": 1}, "items": {"Leftovers": 1}, "moves": {"Psychic": 1, "Hidden Power Fire": 0.7413, "Heal Bell": 0.4607, "Yawn": 0.4603, "Calm Mind": 0.383, "Light Screen": 0.3713, "Reflect": 0.3642, "Toxic": 0.2192}, "evs": {"atk": 0}},
  "Claydol": {"level": 81, "abilities": {"Levitate": 1}, "items": {"Leftovers": 1}, "moves": {"Earthquake": 1, "Psychic": 0.6948, "Ice Beam": 0.5912, "Explosion": 0.5792, "Toxic": 0.5762, "Rapid Spin": 0.5586}},
  "Clefable": {"level": 84, "abilities": {"Cute Charm": 1}, "items": {"Leftovers": 1}, "moves": {"Soft-Boiled": 0.7775, "Return": 0.7689, "Thunderbolt": 0.5653, "Ice Beam": 0.547, "Shadow Ball": 0.4159, "Counter": 0.4025, "Thunder Wave": 0.3767, "Calm Mind": 0.1462}},
  "Cloyster": {"level": 81, "abilities": {"Shell Armor": 1}, "items": {"Leftovers": 1}, "moves": {"Surf": 1, "Ice Beam": 0.7105, "Explosion": 0.5968, "Toxic": 0.5775, "Spikes": 0.5596, "Rapid Spin": 0.5555}},
  "Corsola": {"level": 94, "abilities": {"Natural Cure": 1}, "items": {"Leftovers": 1}, "moves": {"Ice Beam": 1, "Recover": 1, "Surf": 1, "Calm Mind": 0.5758, "Toxic": 0.4242}, "evs": {"atk": 0}, "ivs": {"atk": 0}},
  "Cradily": {"level": 84, "abilities": {"Suction Cups": 1}, "items": {"Leftovers": 1}, "moves": {"Recover": 1, "Rock Slide": 1, "Hidden Power Grass": 0.8037, "Earthquake": 0.4273, "Mirror Coat": 0.3688, "Toxic": 0.3553, "Barrier": 0.0449}},
  "Crawdaunt": {"level": 88, "abilities": {"Hyper Cutter": 0.6622, "Shell Armor": 0.3378}, "items": {"Leftovers": 0.9354, "Choice Band": 0.0646}, "moves": {"Surf": 1, "Crunch": 0.7083, "Ice Beam": 0.5817, "Double-Edge": 0.5761, "Hidden Power Ghost": 0.5682, "Brick Break": 0.5656}},
  "Crobat": {"level": 82, "abilities": {"Inner Focus": 1}, "items": {"Leftovers": 0.9728, "Choice Band": 0.0272}, "moves": {"Aerial Ace": 0.6563, "Sludge Bomb": 0.6485, "Taunt": 0.5464, "Haze": 0.5441, "Toxic": 0.5386, "Shadow Ball": 0.5355, "Hidden Power Ground": 0.5305}},
  "Delcatty": {"level": 93, "abilities": {"Cute Charm": 1}, "items": {"Leftovers": 1}, "moves": {"Double-Edge": 1, "Wish": 1, "Thunder Wave": 0.7071, "Heal Bell": 0.6719, "Baton Pass": 0.6211}},
  "Delibird": {"level": 95, "abilities": {"Hustle": 1}, "items": {"Choice Band": 1}, "moves": {"Aerial Ace": 1, "Hidden Power Ground": 1, "Quick Attack": 1, "Ice Beam": 0.7974, "Focus Punch": 0.2026}, "ivs": {"spa": 30, "spd": 30}},
  "Deoxys": {"level": 74, "abilities": {"Pressure": 1}, "items": {"White Herb": 0.9061, "Choice Band": 0.0939}, "moves": {"Psycho Boost": 1, "Extreme Speed": 0.6033, "Ice Beam": 0.602, "Fire Punch": 0.5996, "Shadow Ball": 0.5978, "Superpower": 0.5972}},
  "Deoxys-Attack": {"level": 74, "abilities": {"Pressure": 1}, "items": {"White Herb": 0.7546, "Choice Band": 0.2454}, "moves": {"Psycho Boost": 1, "Shadow Ball": 0.761, "Fire Punch": 0.7546, "Extreme Speed": 0.7444, "Superpower": 0.7399}},
  "Deoxys-Defense": {"level": 75, "abilities": {"Pressure": 1}, "items": {"Leftovers": 1}, "moves": {"Recover": 1, "Seismic Toss": 0.9568, "Taunt": 0.6983, "Toxic": 0.6828, "Spikes": 0.6622}, "evs": {"atk": 0}, "ivs": {"atk": 0}},
  "Deoxys-Speed": {"level": 76, "abilities": {"Pressure": 1}, "items": {"Leftovers": 1}, "moves": {"Psychic": 1, "Recover": 1, "Ice Beam": 0.6528, "Taunt": 0.3678, "Toxic": 0.3559, "Spikes": 0.3135, "Calm Mind": 0.3101}, "evs": {"atk": 0}, "ivs": {"atk": 0}},
  "Dewgong": {"level": 88, "abilities": {"Thick Fat": 1}, "items": {"Leftovers": 0.902, "Chesto Berry": 0.098}, "moves": {"Surf": 1, "Ice Beam": 0.7469, "Rest": 0.5232, "Toxic": 0.4597, "Hidden Power Grass": 0.4583, "Sleep Talk": 0.4252, "Encore": 0.3866}, "evs": {"atk": 0}},
  "Ditto": {"level": 100, "abilities": {"Limber": 1}, "items": {"Quick Claw": 0.5057, "Metal Powder": 0.4943}, "moves": {"Transform": 1}},
  "Dodrio": {"level": 81, "abilities": {"Early Bird": 1}, "items": {"Salac Berry": 0.5052, "Leftovers": 0.304, "Choice Band": 0.1908}, "moves": {"Drill Peck": 1, "Hidden Power Ground": 1, "Substitute": 0.8092, "Flail": 0.5052, "Return": 0.4948, "Quick Attack": 0.1908}, "ivs": {"spa": 30, "spd": 30}},
  "Donphan": {"level": 83, "abilities": {"Sturdy": 1}, "items": {"Leftovers": 0.8707, "Chesto Berry": 0.1293}, "moves": {"Earthquake": 1, "Rest": 0.7424, "Rock Slide": 0.7404, "Toxic": 0.6301, "Sleep Talk": 0.6131, "Rapid Spin": 0.2739}},
  "Dragonite": {"level": 78, "abilities": {"Inner Focus": 1}, "items": {"Leftovers": 0.7209, "Lum Berry": 0.2622, "Choice Band": 0.017}, "moves": {"Hidden Power Flying": 1, "Flamethrower": 0.7182, "Earthquake": 0.6613, "Ice Beam": 0.5153, "Substitute": 0.4383, "Heal Bell": 0.3233, "Dragon Dance": 0.2622, "Double-Edge": 0.0815}, "ivs": {"hp": 30, "atk": 30, "def": 30, "spa": 30, "spd": 30}},
  "Dugtrio": {"level": 81, "abilities": {"Arena Trap": 1}, "items": {"Liechi Berry": 0.7925, "Choice Band": 0.2075}, "moves": {"Earthquake": 1, "Substitute": 0.7925, "Hidden Power Bug": 0.7369, "Aerial Ace": 0.7363, "Rock Slide": 0.7342}},
  "Dunsparce": {"level": 88, "abilities": {"Serene Grace": 1}, "items": {"Chesto Berry": 0.4234, "Leftovers": 0.4226, "Choice Band": 0.1539}, "moves": {"Body Slam": 0.9266, "Curse": 0.7161, "Shadow Ball": 0.6639, "Rock Slide": 0.6392, "Headbutt": 0.5574, "Rest": 0.4234, "Thunder Wave": 0.0734}},
  "Dusclops": {"level": 86, "abilities": {"Pressure": 1}, "items": {"Leftovers": 0.8896, "Chesto Berry": 0.1104}, "moves": {"Shadow Ball": 1, "Ice Beam": 0.6605, "Will-O-Wisp": 0.5184, "Rest": 0.4957, "Substitute": 0.3891, "Pain Split": 0.3872, "Sleep Talk": 0.3853, "Focus Punch": 0.1638}},
  "Dustox": {"level": 94, "abilities": {"Shield Dust": 1}, "items": {"Leftovers": 1}, "moves": {"Sludge Bomb": 1, "Moonlight": 0.8024, "Toxic": 0.7459, "Whirlwind": 0.7336, "Hidden Power Ground": 0.7182}},
  "Electabuzz": {"level": 83, "abilities": {"Static": 1}, "items": {"Leftovers": 0.694, "Petaya Berry": 0.306}, "moves": {"Thunderbolt": 1, "Substitute": 0.722, "Fire Punch": 0.5588, "Hidden Power Grass": 0.554, "Ice Punch": 0.5422, "Cross Chop": 0.3226, "Focus Punch": 0.3003}},
  "Electrode": {"level": 84, "abilities": {"Static": 1}, "items": {"Leftovers": 1}, "moves": {"Thunderbolt": 1, "Toxic": 0.7749, "Substitute": 0.6709, "Hidden Power Grass": 0.4446, "Thunder Wave": 0.4398, "Hidden Power Ice": 0.4076, "Explosion": 0.2622}},
  "Entei": {"level": 79, "abilities": {"Pressure": 1}, "items": {"Leftovers": 1}, "moves": {"Substitute": 0.8054, "Flamethrower": 0.6712, "Calm Mind": 0.5617, "Hidden Power Ice": 0.3696, "Sunny Day": 0.3463, "Solar Beam": 0.3456, "Fire Blast": 0.3288, "Hidden Power Grass": 0.3245, "Body Slam": 0.2469}},
  "Espeon": {"level": 78, "abilities": {"Synchronize": 1}, "items": {"Leftovers": 1}, "moves": {"Psychic": 1, "Morning Sun": 0.858, "Hidden Power Fire": 0.7127, "Calm Mind": 0.6912, "Baton Pass": 0.4401, "Reflect": 0.298}, "evs": {"atk": 0}},
  "Exeggutor": {"level": 82, "abilities": {"Chlorophyll": 1}, "items": {"Leftovers": 1}, "moves": {"Psychic": 1, "Giga Drain": 0.7249, "Sunny Day": 0.505, "Solar Beam": 0.4986, "Sleep Powder": 0.3308, "Explosion": 0.2762, "Hidden Power Fire": 0.2281, "Hidden Power Ice": 0.2274, "Leech Seed": 0.2091}},
  "Exploud": {"level": 84, "abilities": {"Soundproof": 1}, "items": {"Leftovers": 0.9233, "Choice Band": 0.0767}, "moves": {"Return": 1, "Substitute": 0.6697, "Earthquake": 0.5754, "Ice Beam": 0.5649, "Shadow Ball": 0.5564, "Flamethrower": 0.5298, "Overheat": 0.1038}},
  "Farfetch’d": {"level": 97, "abilities": {"Inner Focus": 1}, "items": {"Stick": 1}, "moves": {"Hidden Power Flying": 1, "Return": 1, "Swords Dance": 0.7923, "Baton Pass": 0.7904, "Agility": 0.4173}, "ivs": {"hp": 30, "atk": 30, "def": 30, "spa": 30, "spd": 30}},
  "Fearow": {"level": 85, "abilities": {"Keen Eye": 1}, "items": {"Leftovers": 0.9302, "Choice Band": 0.0698}, "moves": {"Return": 0.8218, "Drill Peck": 0.8214, "Hidden Power Ground": 0.7035, "Substitute": 0.67, "Baton Pass": 0.6532, "Agility": 0.2602, "Quick Attack": 0.0698}},
  "Feraligatr": {"level": 83, "abilities": {"Torrent": 1}, "items": {"Salac Berry": 0.8019, "Choice Band": 0.1981}, "moves": {"Hydro Pump": 0.8095, "Rock Slide": 0.8076, "Swords Dance": 0.8019, "Earthquake": 0.7981, "Hidden Power Flying": 0.7829}},
  "Flareon": {"level": 88, "abilities": {"Flash Fire": 1}, "items": {"Leftovers": 1}, "moves": {"Fire Blast": 1, "Wish": 0.8858, "Protect": 0.6236, "Shadow Ball": 0.5275, "Hidden Power Grass": 0.5002, "Toxic": 0.4042, "Double-Edge": 0.0587}},
  "Flygon": {"level": 79, "abilities": {"Levitate": 1}, "items": {"Leftovers": 0.9268, "Choice Band": 0.0732}, "moves": {"Earthquake": 1, "Substitute": 0.6515, "Dragon Claw": 0.6406, "Fire Blast": 0.4289, "Rock Slide": 0.4271, "Toxic": 0.4268, "Hidden Power Bug": 0.4251}},
  "Forretress": {"level": 81, "abilities": {"Sturdy": 1}, "items": {"Leftovers": 0.7361, "Choice Band": 0.2639}, "moves": {"Hidden Power Bug": 1, "Earthquake": 0.7285, "Explosion": 0.7164, "Rapid Spin": 0.6997, "Toxic": 0.4483, "Spikes": 0.4071}, "ivs": {"atk": 30, "def": 30, "spd": 30}},
  "Furret": {"level": 90, "abilities": {"Keen Eye": 1}, "items": {"Salac Berry": 0.7909, "Choice Band": 0.2091}, "moves": {"Shadow Ball": 1, "Return": 0.828, "Reversal": 0.7909, "Substitute": 0.7909, "Quick Attack": 0.2091, "Trick": 0.2091, "Double-Edge": 0.172}},
  "Gardevoir": {"level": 79, "abilities": {"Trace": 0.6714, "Synchronize": 0.3286}, "items": {"Leftovers": 0.9887, "Petaya Berry": 0.0113}, "moves": {"Psychic": 1, "Fire Punch": 0.6601, "Thunderbolt": 0.6509, "Calm Mind": 0.6114, "Hypnosis": 0.4815, "Substitute": 0.4669, "Will-O-Wisp": 0.1292}, "evs": {"atk": 0}, "ivs": {"atk": 0}},
  "Gengar": {"level": 78, "abilities": {"Levitate": 1}, "items": {"Leftovers": 0.9699, "Petaya Berry": 0.0301}, "moves": {"Ice Punch": 0.6586, "Thunderbolt": 0.6394, "Fire Punch": 0.6309, "Substitute": 0.5796, "Hypnosis": 0.5614, "Destiny Bond": 0.3818, "Will-O-Wisp": 0.3019, "Explosion": 0.2464}},
  "Girafarig": {"level": 85, "abilities": {"Early Bird": 0.6508, "Inner Focus": 0.3492}, "items": {"Leftovers": 1}, "moves": {"Psychic": 1, "Baton Pass": 0.7085, "Wish": 0.6837, "Substitute": 0.5359, "Calm Mind": 0.3532, "Thunderbolt": 0.3496, "Thunder Wave": 0.2006, "Agility": 0.1685}, "evs": {"atk": 0}, "ivs": {"atk": 0}},
  "Glalie": {"level": 84, "abilities": {"Inner Focus": 1}, "items": {"Leftovers": 1}, "moves": {"Ice Beam": 1, "Earthquake": 0.7656, "Explosion": 0.7638, "Toxic": 0.7613, "Spikes": 0.7093}},
  "Gligar": {"level": 84, "abilities": {"Hyper Cutter": 0.9937, "Sand Veil": 0.0063}, "items": {"Leftovers": 0.7043, "Salac Berry": 0.1759, "Choice Band": 0.1198}, "moves": {"Earthquake": 1, "Substitute": 0.7043, "Swords Dance": 0.6976, "Hidden Power Flying": 0.6908, "Iron Tail": 0.4264, "Rock Slide": 0.3965, "Quick Attack": 0.0844}},
  "Golduck": {"level": 82, "abilities": {"Cloud Nine": 1}, "items": {"Leftovers": 0.9977, "Petaya Berry": 0.0023}, "moves": {"Calm Mind": 0.743, "Ice Beam": 0.6836, "Hidden Power Grass": 0.6776, "Surf": 0.6337, "Hypnosis": 0.5299, "Hydro Pump": 0.3663, "Substitute": 0.3658}, "evs": {"atk": 0}},
  "Golem": {"level": 84, "abilities": {"Rock Head": 1}, "items": {"Choice Band": 0.5104, "Leftovers": 0.4896}, "moves": {"Earthquake": 1, "Rock Slide": 1, "Hidden Power Bug": 0.6029, "Explosion": 0.5781, "Toxic": 0.4896, "Double-Edge": 0.3294}},
  "Gorebyss": {"level": 85, "abilities": {"Swift Swim": 1}, "items": {"Petaya Berry": 1}, "moves": {"Ice Beam": 1, "Rain Dance": 1, "Surf": 0.5237, "Hidden Power Electric": 0.5013, "Hidden Power Grass": 0.4987, "Hydro Pump": 0.4763}, "evs": {"atk": 0}, "ivs": {"spa": 30}},
  "Granbull": {"level": 83, "abilities": {"Intimidate": 1}, "items": {"Chesto Berry": 0.6444, "Leftovers": 0.336, "Choice Band": 0.0196}, "moves": {"Return": 1, "Rest": 0.6444, "Shadow Ball": 0.536, "Earthquake": 0.5222, "Bulk Up": 0.419, "Overheat": 0.3794, "Thunder Wave": 0.3196, "Heal Bell": 0.1794}},
  "Groudon": {"level": 70, "abilities": {"Drought": 1}, "items": {"Leftovers": 0.806, "Salac Berry": 0.1682, "Choice Band": 0.0258}, "moves": {"Earthquake": 1, "Substitute": 0.6965, "Hidden Power Bug": 0.6225, "Rock Slide": 0.6161, "Swords Dance": 0.5183, "Thunder Wave": 0.3428, "Overheat": 0.2037}},
  "Grumpig": {"level": 84, "abilities": {"Thick Fat": 1}, "items": {"Leftovers": 0.9929, "Petaya Berry": 0.0071}, "moves": {"Psychic": 1, "Fire Punch": 0.9437, "Calm Mind": 0.6779, "Taunt": 0.5677, "Substitute": 0.5505, "Icy Wind": 0.2603}, "evs": {"atk": 0}, "ivs": {"atk": 0}},
  "Gyarados": {"level": 75, "abilities": {"Intimidate": 1}, "items": {"Lum Berry": 0.8058, "Choice Band": 0.1942}, "moves": {"Earthquake": 1, "Hidden Power Flying": 1, "Hydro Pump": 1, "Dragon Dance": 0.8058, "Double-Edge": 0.1942}, "ivs": {"hp": 30, "atk": 30, "def": 30, "spa": 30, "spd": 30}},
  "Hariyama": {"level": 83, "abilities": {"Thick Fat": 0.6693, "Guts": 0.3307}, "items": {"Leftovers": 0.839, "Chesto Berry": 0.161}, "moves": {"Cross Chop": 1, "Bulk Up": 0.76, "Rest": 0.6244, "Hidden Power Ghost": 0.5376, "Rock Slide": 0.5337, "Sleep Talk": 0.4634, "Fake Out": 0.081}},
  "Heracross": {"level": 80, "abilities": {"Guts": 1}, "items": {"Leftovers": 0.6472, "Chesto Berry": 0.1876, "Salac Berry": 0.131, "Choice Band": 0.0342}, "moves": {"Megahorn": 0.8986, "Swords Dance": 0.771, "Brick Break": 0.761, "Rest": 0.5664, "Sleep Talk": 0.3788, "Substitute": 0.2684, "Rock Slide": 0.2617, "Focus Punch": 0.0941}},
  "Hitmonchan": {"level": 87, "abilities": {"Keen Eye": 1}, "items": {"Leftovers": 0.8579, "Choice Band": 0.1421}, "moves": {"Sky Uppercut": 1, "Mach Punch": 0.7719, "Bulk Up": 0.6511, "Hidden Power Ghost": 0.5938, "Earthquake": 0.5854, "Toxic": 0.2068, "Rapid Spin": 0.1909}},
  "Hitmonlee": {"level": 85, "abilities": {"Limber": 1}, "items": {"Salac Berry": 0.4625, "Leftovers": 0.4096, "Choice Band": 0.1279}, "moves": {"High Jump Kick": 1, "Bulk Up": 0.6977, "Substitute": 0.6369, "Rock Slide": 0.4858, "Hidden Power Ghost": 0.4751, "Earthquake": 0.4665, "Mach Punch": 0.238}},
  "Hitmontop": {"level": 85, "abilities": {"Intimidate": 1}, "items": {"Leftovers": 0.8514, "Choice Band": 0.1486}, "moves": {"High Jump Kick": 1, "Mach Punch": 0.704, "Bulk Up": 0.6451, "Earthquake": 0.4845, "Hidden Power Ghost": 0.4833, "Rock Slide": 0.4767, "Toxic": 0.2064}},
  "Ho-Oh": {"level": 72, "abilities": {"Pressure": 1}, "items": {"Leftovers": 1}, "moves": {"Recover": 1, "Sacred Fire": 1, "Substitute": 0.5402, "Thunderbolt": 0.4549, "Earthquake": 0.3863, "Toxic": 0.3467, "Calm Mind": 0.2717}},
  "Houndoom": {"level": 81, "abilities": {"Flash Fire": 1}, "items": {"Leftovers": 1}, "moves": {"Crunch": 0.7725, "Pursuit": 0.7628, "Will-O-Wisp": 0.7415, "Hidden Power Grass": 0.7232, "Flamethrower": 0.5133, "Fire Blast": 0.4867}, "evs": {"atk": 0}},
  "Huntail": {"level": 88, "abilities": {"Swift Swim": 1}, "items": {"Petaya Berry": 0.7707, "Leftovers": 0.2293}, "moves": {"Hidden Power Grass": 1, "Ice Beam": 1, "Rain Dance": 0.7707, "Surf": 0.5964, "Hydro Pump": 0.4036, "Double-Edge": 0.2293}, "ivs": {"spa": 30}},
  "Hypno": {"level": 86, "abilities": {"Insomnia": 1}, "items": {"Leftovers": 1}, "moves": {"Psychic": 1, "Wish": 0.8581, "Baton Pass": 0.6111, "Calm Mind": 0.4376, "Fire Punch": 0.397, "Protect": 0.3051, "Hypnosis": 0.2718, "Toxic": 0.1192}, "evs": {"atk": 0}, "ivs": {"atk": 0}},
  "Illumise": {"level": 94, "abilities": {"Oblivious": 1}, "items": {"Leftovers": 1}, "moves": {"Ice Punch": 1, "Wish": 0.7398, "Substitute": 0.7335, "Baton Pass": 0.627, "Encore": 0.4553, "Thunder Wave": 0.4443}, "evs": {"atk": 0}, "ivs": {"atk": 0}},
  "Jirachi": {"level": 74, "abilities": {"Serene Grace": 1}, "items": {"Leftovers": 0.9952, "Petaya Berry": 0.0048}, "moves": {"Psychic": 1, "Wish": 0.7332, "Calm Mind": 0.4148, "Substitute": 0.3877, "Thunderbolt": 0.3445, "Fire Punch": 0.3352, "Ice Punch": 0.3323, "Protect": 0.2281, "Body Slam": 0.2242}},
  "Jolteon": {"level": 79, "abilities": {"Volt Absorb": 1}, "items": {"Leftovers": 1}, "moves": {"Thunderbolt": 1, "Wish": 0.7387, "Substitute": 0.7197, "Baton Pass": 0.6199, "Toxic": 0.4715, "Hidden Power Ice": 0.4503}, "evs": {"atk": 0}},
  "Jumpluff": {"level": 85, "abilities": {"Chlorophyll": 1}, "items": {"Leftovers": 1}, "moves": {"Hidden Power Flying": 1, "Substitute": 0.7132, "Leech Seed": 0.5838, "Sleep Powder": 0.5728, "Encore": 0.5685, "Toxic": 0.5617}, "ivs": {"hp": 30, "atk": 30, "def": 30, "spa": 30, "spd": 30}},
  "Jynx": {"level": 82, "abilities": {"Oblivious": 1}, "items": {"Leftovers": 0.9958, "Petaya Berry": 0.0042}, "moves": {"Psychic": 1, "Calm Mind": 0.7945, "Ice Beam": 0.7761, "Hidden Power Fire": 0.5394, "Substitute": 0.4533, "Lovely Kiss": 0.4367}, "evs": {"atk": 0}},
  "Kabutops": {"level": 84, "abilities": {"Battle Armor": 0.9553, "Swift Swim": 0.0447}, "items": {"Salac Berry": 0.7254, "Choice Band": 0.2746}, "moves": {"Rock Slide": 1, "Surf": 0.8379, "Swords Dance": 0.7254, "Hidden Power Ground": 0.632, "Brick Break": 0.6169, "Double-Edge": 0.1878}},
  "Kangaskhan": {"level": 79, "abilities": {"Early Bird": 1}, "items": {"Leftovers": 0.9794, "Choice Band": 0.0206}, "moves": {"Return": 1, "Fake Out": 0.7011, "Rest": 0.6332, "Shadow Ball": 0.4887, "Earthquake": 0.4727, "Toxic": 0.3549, "Substitute": 0.2495, "Focus Punch": 0.0998}},
  "Kecleon": {"level": 91, "abilities": {"Color Change": 1}, "items": {"Leftovers": 0.7528, "Choice Band": 0.2472}, "moves": {"Brick Break": 1, "Return": 1, "Shadow Ball": 1, "Thunder Wave": 0.7528, "Trick": 0.2472}},
  "Kingdra": {"level": 82, "abilities": {"Swift Swim": 1}, "items": {"Leftovers": 0.5327, "Petaya Berry": 0.4673}, "moves": {"Substitute": 0.7718, "Rain Dance": 0.7609, "Ice Beam": 0.743, "Hidden Power Grass": 0.7243, "Surf": 0.629, "Hydro Pump": 0.371}, "evs": {"atk": 0}},
  "Kingler": {"level": 90, "abilities": {"Hyper Cutter": 0.6599, "Shell Armor": 0.3401}, "items": {"Salac Berry": 1}, "moves": {"Double-Edge": 1, "Surf": 1, "Swords Dance": 1, "Hidden Power Ghost": 0.5011, "Hidden Power Ground": 0.4989}, "ivs": {"spd": 30}},
  "Kyogre": {"level": 67, "abilities": {"Drizzle": 1}, "items": {"Leftovers": 0.8611, "Chesto Berry": 0.1389}, "moves": {"Surf": 1, "Calm Mind": 0.7965, "Rest": 0.6489, "Ice Beam": 0.5263, "Thunder": 0.5183, "Sleep Talk": 0.51}, "evs": {"atk": 0}, "ivs": {"atk": 0}},
  "Lanturn": {"level": 82, "abilities": {"Volt Absorb": 1}, "items": {"Leftovers": 0.8795, "Chesto Berry": 0.1205}, "moves": {"Surf": 1, "Thunderbolt": 1, "Rest": 0.5372, "Sleep Talk": 0.4167, "Ice Beam": 0.268, "Thunder Wave": 0.2623, "Toxic": 0.2611, "Confuse Ray": 0.2546}, "evs": {"atk": 0}, "ivs": {"atk": 0}},
  "Lapras": {"level": 81, "abilities": {"Water Absorb": 1}, "items": {"Leftovers": 0.8811, "Chesto Berry": 0.1189}, "moves": {"Surf": 1, "Ice Beam": 0.7753, "Rest": 0.538, "Thunderbolt": 0.4986, "Toxic": 0.4799, "Sleep Talk": 0.4191, "Heal Bell": 0.2891}, "evs": {"atk": 0}, "ivs": {"atk": 0}},
  "Latias": {"level": 67, "abilities": {"Levitate": 1}, "items": {"Soul Dew": 1}, "moves": {"Psychic": 1, "Recover": 1, "Calm Mind": 0.7988, "Dragon Claw": 0.7906, "Hidden Power Fire": 0.4106}, "evs": {"atk": 0}},
  "Latios": {"level": 66, "abilities": {"Levitate": 1}, "items": {"Soul Dew": 1}, "moves": {"Psychic": 1, "Recover": 1, "Dragon Claw": 0.7982, "Calm Mind": 0.7895, "Hidden Power Fire": 0.4122}, "evs": {"atk": 0}},
  "Ledian": {"level": 97, "abilities": {"Swarm": 0.6539, "Early Bird": 0.3461}, "items": {"Leftovers": 1}, "moves": {"Silver Wind": 1, "Baton Pass": 0.7134, "Swords Dance": 0.6326, "Reflect": 0.4532, "Toxic": 0.442, "Light Screen": 0.4221, "Agility": 0.3366}},
  "Lickitung": {"level": 91, "abilities": {"Own Tempo": 1}, "items": {"Leftovers": 1}, "moves": {"Wish": 0.8879, "Return": 0.745, "Seismic Toss": 0.6147, "Protect": 0.5378, "Heal Bell": 0.4665, "Toxic": 0.4253, "Counter": 0.3228}},
  "Linoone": {"level": 85, "abilities": {"Pickup": 1}, "items": {"Salac Berry": 0.8831, "Leftovers": 0.1169}, "moves": {"Substitute": 0.7912, "Extreme Speed": 0.7706, "Hidden Power Ground": 0.6783, "Belly Drum": 0.668, "Shadow Ball": 0.6546, "Flail": 0.4373}},
  "Ludicolo": {"level": 83, "abilities": {"Swift Swim": 1}, "items": {"Leftovers": 0.8155, "Petaya Berry": 0.1845}, "moves": {"Surf": 1, "Hidden Power Grass": 0.7312, "Substitute": 0.7025, "Leech Seed": 0.5425, "Ice Beam": 0.5138, "Rain Dance": 0.5099}, "evs": {"atk": 0}},
  "Lugia": {"level": 70, "abilities": {"Pressure": 1}, "items": {"Leftovers": 1}, "moves": {"Recover": 1, "Aeroblast": 0.7956, "Substitute": 0.5276, "Thunderbolt": 0.4446, "Ice Beam": 0.4362, "Earthquake": 0.4024, "Toxic": 0.3373, "Calm Mind": 0.0563}},
  "Lunatone": {"level": 84, "abilities": {"Levitate": 1}, "items": {"Leftovers": 1}, "moves": {"Ice Beam": 1, "Psychic": 1, "Calm Mind": 0.7476, "Baton Pass": 0.487, "Hypnosis": 0.4797, "Explosion": 0.2857}},
  "Luvdisc": {"level": 98, "abilities": {"Swift Swim": 1}, "items": {"Leftovers": 1}, "moves": {"Surf": 1, "Substitute": 0.7523, "Ice Beam": 0.6488, "Toxic": 0.6474, "Sweet Kiss": 0.6172, "Protect": 0.3341}, "evs": {"atk": 0}, "ivs": {"atk": 0}},
  "Machamp": {"level": 84, "abilities": {"Guts": 1}, "items": {"Leftovers": 0.8143, "Chesto Berry": 0.1116, "Choice Band": 0.0741}, "moves": {"Cross Chop": 1, "Bulk Up": 0.7458, "Rest": 0.5328, "Hidden Power Ghost": 0.4406, "Earthquake": 0.43, "Rock Slide": 0.4297, "Sleep Talk": 0.4211}},
  "Magcargo": {"level": 93, "abilities": {"Flame Body": 1}, "items": {"Leftovers": 0.8067, "Chesto Berry": 0.1933}, "moves": {"Fire Blast": 1, "Rest": 0.8305, "Hidden Power Grass": 0.7604, "Sleep Talk": 0.6372, "Toxic": 0.4464, "Yawn": 0.3256}, "evs": {"atk": 0}},
  "Magmar": {"level": 84, "abilities": {"Flame Body": 1}, "items": {"Leftovers": 0.6799, "Petaya Berry": 0.3201}, "moves": {"Substitute": 0.6634, "Cross Chop": 0.5983, "Psychic": 0.588, "Thunder Punch": 0.5764, "Hidden Power Grass": 0.574, "Fire Blast": 0.5113, "Flamethrower": 0.4887}},
  "Magneton": {"level": 84, "abilities": {"Magnet Pull": 1}, "items": {"Leftovers": 0.6888, "Chesto Berry": 0.3112}, "moves": {"Rest": 1, "Thunderbolt": 1, "Sleep Talk": 0.6888, "Toxic": 0.5698, "Hidden Power Ice": 0.3718, "Hidden Power Grass": 0.3696}, "evs": {"atk": 0}},
  "Manectric": {"level": 83, "abilities": {"Static": 1}, "items": {"Leftovers": 0.6698, "Petaya Berry": 0.3302}, "moves": {"Thunderbolt": 1, "Substitute": 0.7723, "Crunch": 0.7002, "Thunder Wave": 0.6698, "Hidden Power Ice": 0.4291, "Hidden Power Grass": 0.4287}, "evs": {"atk": 0}},
  "Mantine": {"level": 85, "abilities": {"Water Absorb": 0.5178, "Swift Swim": 0.4822}, "items": {"Leftovers": 0.6387, "Petaya Berry": 0.1958, "Chesto Berry": 0.1655}, "moves": {"Surf": 1, "Hidden Power Grass": 0.6369, "Ice Beam": 0.6346, "Rest": 0.5656, "Sleep Talk": 0.4001, "Toxic": 0.3446, "Haze": 0.2224, "Rain Dance": 0.1958}, "evs": {"atk": 0}},
  "Marowak": {"level": 82, "abilities": {"Rock Head": 1}, "items": {"Thick Club": 1}, "moves": {"Bonemerang": 1, "Rock Slide": 1, "Swords Dance": 1, "Double-Edge": 0.51, "Earthquake": 0.49}},
  "Masquerain": {"level": 93, "abilities": {"Intimidate": 1}, "items": {"Leftovers": 1}, "moves": {"Hydro Pump": 1, "Ice Beam": 1, "Substitute": 1, "Toxic": 0.6656, "Stun Spore": 0.3344}, "evs": {"atk": 0}, "ivs": {"atk": 0}},
  "Mawile": {"level": 94, "abilities": {"Intimidate": 1}, "items": {"Leftovers": 0.962, "Choice Band": 0.038}, "moves": {"Hidden Power Steel": 1, "Substitute": 0.7311, "Swords Dance": 0.6426, "Baton Pass": 0.6276, "Rock Slide": 0.427, "Brick Break": 0.2864, "Focus Punch": 0.1516, "Toxic": 0.1338}, "ivs": {"spd": 30}},
  "Medicham": {"level": 83, "abilities": {"Pure Power": 1}, "items": {"Leftovers": 0.832, "Salac Berry": 0.168}, "moves": {"Brick Break": 1, "Recover": 1, "Substitute": 0.7485, "Rock Slide": 0.4541, "Shadow Ball": 0.4459, "Bulk Up": 0.3515}},
  "Meganium": {"level": 84, "abilities": {"Overgrow": 1}, "items": {"Leftovers": 1}, "moves": {"Hidden Power Grass": 1, "Synthesis": 0.7953, "Toxic": 0.7378, "Body Slam": 0.7361, "Leech Seed": 0.7308}, "ivs": {"spa": 30}},
  "Metagross": {"level": 76, "abilities": {"Clear Body": 1}, "items": {"Leftovers": 0.6982, "Choice Band": 0.3018}, "moves": {"Meteor Mash": 1, "Psychic": 0.7041, "Agility": 0.6982, "Explosion": 0.5416, "Rock Slide": 0.5289, "Earthquake": 0.5271}},
  "Mew": {"level": 73, "abilities": {"Synchronize": 1}, "items": {"Leftovers": 1}, "moves": {"Psychic": 1, "Soft-Boiled": 0.6528, "Thunderbolt": 0.4349, "Ice Beam": 0.4265, "Flamethrower": 0.42, "Calm Mind": 0.3693, "Thunder Wave": 0.2941, "Transform": 0.2757, "Explosion": 0.1268}},
  "Mewtwo": {"level": 66, "abilities": {"Pressure": 1}, "items": {"Leftovers": 1}, "moves": {"Psychic": 1, "Recover": 1, "Calm Mind": 0.469, "Substitute": 0.4645, "Flamethrower": 0.3697, "Ice Beam": 0.3514, "Thunderbolt": 0.3454}, "evs": {"atk": 0}, "ivs": {"atk": 0}},
  "Mightyena": {"level": 90, "abilities": {"Intimidate": 1}, "items": {"Leftovers": 0.8917, "Choice Band": 0.1083}, "moves": {"Crunch": 1, "Hidden Power Fighting": 0.6857, "Shadow Ball": 0.6855, "Toxic": 0.6577, "Heal Bell": 0.5415, "Protect": 0.3213, "Double-Edge": 0.1083}},
  "Milotic": {"level": 78, "abilities": {"Marvel Scale": 1}, "items": {"Leftovers": 1}, "moves": {"Ice Beam": 1, "Recover": 1, "Surf": 1, "Toxic": 0.6779, "Mirror Coat": 0.3221}, "evs": {"atk": 0}, "ivs": {"atk": 0}},
  "Miltank": {"level": 78, "abilities": {"Thick Fat": 1}, "items": {"Leftovers": 1}, "moves": {"Body Slam": 1, "Earthquake": 0.8581, "Milk Drink": 0.8061, "Curse": 0.4981, "Heal Bell": 0.468, "Toxic": 0.3697}},
  "Minun": {"level": 89, "abilities": {"Minus": 1}, "items": {"Leftovers": 1}, "moves": {"Thunderbolt": 1, "Substitute": 0.6721, "Wish": 0.6597, "Baton Pass": 0.5398, "Hidden Power Ice": 0.3811, "Light Screen": 0.3751, "Encore": 0.3722}, "evs": {"atk": 0}},
  "Misdreavus": {"level": 85, "abilities": {"Levitate": 1}, "items": {"Leftovers": 1}, "moves": {"Thunderbolt": 0.7814, "Hidden Power Ice": 0.7752, "Toxic": 0.6601, "Protect": 0.5439, "Substitute": 0.4441, "Mean Look": 0.2954, "Perish Song": 0.2936, "Calm Mind": 0.2062}, "evs": {"atk": 0}},
  "Moltres": {"level": 79, "abilities": {"Pressure": 1}, "items": {"Leftovers": 1}, "moves": {"Morning Sun": 1, "Substitute": 0.7372, "Flamethrower": 0.7143, "Hidden Power Grass": 0.513, "Toxic": 0.4584, "Will-O-Wisp": 0.2915, "Fire Blast": 0.2857}, "evs": {"atk": 0}},
  "Mr. Mime": {"level": 84, "abilities": {"Soundproof": 1}, "items": {"Leftovers": 0.9898, "Petaya Berry": 0.0102}, "moves": {"Psychic": 1, "Substitute": 0.5163, "Calm Mind": 0.46, "Baton Pass": 0.4532, "Fire Punch": 0.4299, "Thunderbolt": 0.4049, "Encore": 0.3283, "Hypnosis": 0.3181, "Barrier": 0.0894}, "evs": {"atk": 0}, "ivs": {"atk": 0}},
  "Muk": {"level": 84, "abilities": {"Sticky Hold": 1}, "items": {"Chesto Berry": 0.4271, "Leftovers": 0.3292, "Choice Band": 0.2437}, "moves": {"Sludge Bomb": 1, "Curse": 0.6288, "Brick Break": 0.5897, "Hidden Power Ghost": 0.5805, "Fire Blast": 0.4658, "Rest": 0.4271, "Explosion": 0.308}},
  "Murkrow": {"level": 90, "abilities": {"Insomnia": 1}, "items": {"Leftovers": 0.7605, "Choice Band": 0.2395}, "moves": {"Drill Peck": 1, "Shadow Ball": 1, "Substitute": 0.7605, "Hidden Power Ground": 0.5065, "Hidden Power Fighting": 0.4935, "Double-Edge": 0.2395}, "ivs": {"spa": 30, "spd": 30}},
  "Nidoking": {"level": 81, "abilities": {"Poison Point": 1}, "items": {"Leftovers": 0.9269, "Choice Band": 0.0731}, "moves": {"Earthquake": 1, "Substitute": 0.644, "Sludge Bomb": 0.6243, "Ice Beam": 0.4363, "Thunderbolt": 0.4335, "Fire Blast": 0.4311, "Megahorn": 0.4307}},
  "Nidoqueen": {"level": 83, "abilities": {"Poison Point": 1}, "items": {"Choice Band": 0.7341, "Leftovers": 0.2659}, "moves": {"Earthquake": 1, "Sludge Bomb": 0.707, "Superpower": 0.5784, "Shadow Ball": 0.576, "Fire Blast": 0.5721, "Ice Beam": 0.5665}},
  "Ninetales": {"level": 82, "abilities": {"Flash Fire": 1}, "items": {"Leftovers": 1}, "moves": {"Hidden Power Grass": 1, "Substitute": 1, "Flamethrower": 0.7777, "Hypnosis": 0.6774, "Fire Blast": 0.2223, "Toxic": 0.2172, "Will-O-Wisp": 0.1054}, "evs": {"atk": 0}, "ivs": {"atk": 2, "spa": 30}},
  "Ninjask": {"level": 84, "abilities": {"Speed Boost": 1}, "items": {"Leftovers": 1}, "moves": {"Aerial Ace": 0.7737, "Substitute": 0.7625, "Silver Wind": 0.7592, "Swords Dance": 0.7018, "Baton Pass": 0.6645, "Protect": 0.3383}},
  "Noctowl": {"level": 91, "abilities": {"Insomnia": 1}, "items": {"Leftovers": 1}, "moves": {"Psychic": 1, "Hidden Power Fire": 0.7079, "Whirlwind": 0.6916, "Reflect": 0.6906, "Hypnosis": 0.6051, "Toxic": 0.3047}, "evs": {"atk": 0}},
  "Nosepass": {"level": 96, "abilities": {"Magnet Pull": 1}, "items": {"Leftovers": 1}, "moves": {"Rock Slide": 1, "Toxic": 0.7539, "Explosion": 0.7524, "Earthquake": 0.747, "Thunder Wave": 0.7467}},
  "Octillery": {"level": 87, "abilities": {"Suction Cups": 1}, "items": {"Leftovers": 1}, "moves": {"Surf": 1, "Thunder Wave": 0.6157, "Fire Blast": 0.6046, "Ice Beam": 0.5962, "Rock Blast": 0.5944, "Hidden Power Grass": 0.589}},
  "Omastar": {"level": 84, "abilities": {"Swift Swim": 0.7914, "Shell Armor": 0.2086}, "items": {"Leftovers": 0.7138, "Petaya Berry": 0.2862}, "moves": {"Rain Dance": 0.7827, "Hidden Power Grass": 0.7548, "Ice Beam": 0.7487, "Spikes": 0.7138, "Surf": 0.6139, "Hydro Pump": 0.3861}, "evs": {"atk": 0}},
  "Parasect": {"level": 93, "abilities": {"Effect Spore": 1}, "items": {"Leftovers": 1}, "moves": {"Giga Drain": 1, "Hidden Power Bug": 0.8651, "Spore": 0.6471, "Return": 0.5728, "Aromatherapy": 0.3579, "Stun Spore": 0.3545, "Swords Dance": 0.2026}},
  "Pelipper": {"level": 88, "abilities": {"Keen Eye": 1}, "items": {"Leftovers": 0.8781, "Chesto Berry": 0.1219}, "moves": {"Surf": 1, "Ice Beam": 0.7503, "Rest": 0.7151, "Sleep Talk": 0.5932, "Toxic": 0.5767, "Protect": 0.3646}, "evs": {"atk": 0}, "ivs": {"atk": 0}},
  "Persian": {"level": 87, "abilities": {"Limber": 1}, "items": {"Leftovers": 0.9636, "Choice Band": 0.0364}, "moves": {"Return": 1, "Fake Out": 0.6488, "Substitute": 0.6483, "Hidden Power Ground": 0.4356, "Shadow Ball": 0.4346, "Iron Tail": 0.429, "Hypnosis": 0.4037}},
  "Pidgeot": {"level": 87, "abilities": {"Keen Eye": 1}, "items": {"Leftovers": 0.9313, "Choice Band": 0.0687}, "moves": {"Aerial Ace": 0.7944, "Return": 0.7916, "Hidden Power Ground": 0.7508, "Toxic": 0.7229, "Substitute": 0.6678, "Quick Attack": 0.2726}},
  "Pikachu": {"level": 88, "abilities": {"Static": 1}, "items": {"Light Ball": 1}, "moves": {"Hidden Power Ice": 1, "Substitute": 1, "Surf": 1, "Thunderbolt": 1}, "evs": {"atk": 0}, "ivs": {"atk": 2, "def": 30}},
  "Piloswine": {"level": 88, "abilities": {"Oblivious": 1}, "items": {"Leftovers": 0.7178, "Choice Band": 0.2822}, "moves": {"Earthquake": 1, "Ice Beam": 0.8271, "Rock Slide": 0.7522, "Toxic": 0.7055, "Protect": 0.433, "Double-Edge": 0.2822}},
  "Pinsir": {"level": 82, "abilities": {"Hyper Cutter": 1}, "items": {"Salac Berry": 0.8141, "Choice Band": 0.1859}, "moves": {"Hidden Power Bug": 1, "Swords Dance": 0.8141, "Return": 0.7347, "Rock Slide": 0.7283, "Earthquake": 0.7229}, "ivs": {"atk": 30, "def": 30, "spd": 30}},
  "Plusle": {"level": 88, "abilities": {"Plus": 1}, "items": {"Leftovers": 1}, "moves": {"Thunderbolt": 1, "Substitute": 0.7351, "Baton Pass": 0.6168, "Hidden Power Grass": 0.5692, "Encore": 0.5352, "Toxic": 0.3487, "Agility": 0.1951}, "evs": {"atk": 0}},
  "Politoed": {"level": 84, "abilities": {"Water Absorb": 1}, "items": {"Chesto Berry": 0.7629, "Leftovers": 0.2371}, "moves": {"Surf": 1, "Rest": 0.7629, "Ice Beam": 0.6902, "Hidden Power Grass": 0.6723, "Hypnosis": 0.5854, "Toxic": 0.2892}, "evs": {"atk": 0}},
  "Poliwrath": {"level": 84, "abilities": {"Water Absorb": 1}, "items": {"Leftovers": 0.7336, "Salac Berry": 0.2664}, "moves": {"Brick Break": 1, "Hydro Pump": 0.84, "Substitute": 0.7418, "Hidden Power Ghost": 0.4383, "Bulk Up": 0.4079, "Ice Beam": 0.2899, "Hypnosis": 0.2821}},
  "Porygon2": {"level": 82, "abilities": {"Trace": 1}, "items": {"Leftovers": 1}, "moves": {"Recover": 1, "Return": 1, "Ice Beam": 0.518, "Thunder Wave": 0.506, "Toxic": 0.4958, "Thunderbolt": 0.4803}},
  "Primeape": {"level": 85, "abilities": {"Vital Spirit": 1}, "items": {"Salac Berry": 0.4688, "Leftovers": 0.4623, "Choice Band": 0.0689}, "moves": {"Cross Chop": 1, "Substitute": 0.7084, "Bulk Up": 0.6915, "Hidden Power Ghost": 0.5427, "Rock Slide": 0.53, "Earthquake": 0.5274}},
  "Quagsire": {"level": 85, "abilities": {"Water Absorb": 1}, "items": {"Chesto Berry": 0.5091, "Leftovers": 0.4909}, "moves": {"Earthquake": 1, "Surf": 0.8891, "Hidden Power Rock": 0.5099, "Rest": 0.5091, "Curse": 0.4126, "Ice Beam": 0.3186, "Toxic": 0.249, "Counter": 0.1117}},
  "Qwilfish": {"level": 85, "abilities": {"Poison Point": 0.9513, "Swift Swim": 0.0487}, "items": {"Salac Berry": 0.5905, "Leftovers": 0.3301, "Choice Band": 0.0794}, "moves": {"Sludge Bomb": 0.8382, "Hydro Pump": 0.7886, "Shadow Ball": 0.7024, "Self-Destruct": 0.6601, "Swords Dance": 0.5905, "Spikes": 0.2904, "Destiny Bond": 0.1298}},
  "Raichu": {"level": 84, "abilities": {"Static": 1}, "items": {"Leftovers": 0.9032, "Petaya Berry": 0.0968}, "moves": {"Thunderbolt": 1, "Substitute": 0.7011, "Encore": 0.4881, "Thunder Wave": 0.4727, "Surf": 0.4423, "Hidden Power Ice": 0.3394, "Hidden Power Grass": 0.3285, "Focus Punch": 0.228}},
  "Raikou": {"level": 74, "abilities": {"Pressure": 1}, "items": {"Leftovers": 0.8772, "Chesto Berry": 0.1142, "Petaya Berry": 0.0085}, "moves": {"Thunderbolt": 1, "Calm Mind": 0.695, "Rest": 0.5324, "Crunch": 0.479, "Sleep Talk": 0.4181, "Hidden Power Ice": 0.3253, "Hidden Power Grass": 0.3032, "Substitute": 0.247}, "evs": {"atk": 0}},
  "Rapidash": {"level": 83, "abilities": {"Flash Fire": 1}, "items": {"Leftovers": 1}, "moves": {"Fire Blast": 1, "Substitute": 1, "Toxic": 1, "Hidden Power Grass": 0.5015, "Hidden Power Rock": 0.4985}},
  "Raticate": {"level": 88, "abilities": {"Guts": 1}, "items": {"Salac Berry": 0.6568, "Leftovers": 0.1856, "Choice Band": 0.1576}, "moves": {"Return": 1, "Substitute": 0.8424, "Hidden Power Ground": 0.5994, "Shadow Ball": 0.5964, "Endeavor": 0.4813, "Reversal": 0.3229, "Quick Attack": 0.1576}},
  "Rayquaza": {"level": 72, "abilities": {"Air Lock": 1}, "items": {"Lum Berry": 0.7911, "Choice Band": 0.2089}, "moves": {"Hidden Power Flying": 1, "Dragon Dance": 0.7911, "Earthquake": 0.7452, "Extreme Speed": 0.7328, "Rock Slide": 0.7309}, "ivs": {"hp": 30, "atk": 30, "def": 30, "spa": 30, "spd": 30}},
  "Regice": {"level": 79, "abilities": {"Clear Body": 1}, "items": {"Leftovers": 0.9082, "Chesto Berry": 0.0918}, "moves": {"Ice Beam": 1, "Thunderbolt": 0.6655, "Toxic": 0.6033, "Rest": 0.5655, "Sleep Talk": 0.4737, "Thunder Wave": 0.3914, "Explosion": 0.3006}},
  "Regirock": {"level": 82, "abilities": {"Clear Body": 1}, "items": {"Chesto Berry": 0.5551, "Leftovers": 0.3915, "Choice Band": 0.0534}, "moves": {"Rock Slide": 1, "Earthquake": 0.9529, "Curse": 0.6278, "Rest": 0.5551, "Explosion": 0.3859, "Thunder Wave": 0.2942, "Superpower": 0.184}},
  "Registeel": {"level": 80, "abilities": {"Clear Body": 1}, "items": {"Leftovers": 1}, "moves": {"Rest": 1, "Seismic Toss": 1, "Sleep Talk": 1, "Toxic": 1}, "evs": {"atk": 0}, "ivs": {"atk": 0}},
  "Relicanth": {"level": 88, "abilities": {"Rock Head": 0.5226, "Swift Swim": 0.4774}, "items": {"Leftovers": 0.7858, "Chesto Berry": 0.1237, "Choice Band": 0.0905}, "moves": {"Rock Slide": 1, "Hidden Power Flying": 0.6391, "Rest": 0.6299, "Earthquake": 0.6201, "Toxic": 0.5142, "Sleep Talk": 0.5062, "Double-Edge": 0.0905}},
  "Rhydon": {"level": 84, "abilities": {"Rock Head": 1}, "items": {"Leftovers": 0.9364, "Choice Band": 0.0636}, "moves": {"Earthquake": 1, "Rock Slide": 1, "Substitute": 0.8102, "Swords Dance": 0.7968, "Megahorn": 0.3294, "Double-Edge": 0.0636}},
  "Roselia": {"level": 93, "abilities": {"Natural Cure": 1}, "items": {"Leftovers": 1}, "moves": {"Giga Drain": 1, "Synthesis": 0.7065, "Hidden Power Fire": 0.6024, "Stun Spore": 0.5941, "Spikes": 0.5497, "Aromatherapy": 0.5473}, "evs": {"atk": 0}},
  "Sableye": {"level": 90, "abilities": {"Keen Eye": 1}, "items": {"Leftovers": 1}, "moves": {"Recover": 1, "Shadow Ball": 0.7917, "Toxic": 0.7448, "Knock Off": 0.7374, "Seismic Toss": 0.7261}},
  "Salamence": {"level": 74, "abilities": {"Intimidate": 1}, "items": {"Lum Berry": 0.834, "Choice Band": 0.166}, "moves": {"Hidden Power Flying": 1, "Dragon Dance": 0.834, "Brick Break": 0.5469, "Earthquake": 0.5418, "Fire Blast": 0.539, "Rock Slide": 0.5383}, "ivs": {"hp": 30, "atk": 30, "def": 30, "spa": 30, "spd": 30}},
  "Sandslash": {"level": 84, "abilities": {"Sand Veil": 1}, "items": {"Salac Berry": 0.694, "Leftovers": 0.2278, "Choice Band": 0.0782}, "moves": {"Earthquake": 1, "Hidden Power Bug": 0.9316, "Rock Slide": 0.9189, "Swords Dance": 0.694, "Rapid Spin": 0.2278, "Toxic": 0.2278}},
  "Sceptile": {"level": 82, "abilities": {"Overgrow": 1}, "items": {"Leftovers": 0.853, "Petaya Berry": 0.147}, "moves": {"Leaf Blade": 1, "Substitute": 0.8311, "Leech Seed": 0.6229, "Hidden Power Ice": 0.5982, "Thunder Punch": 0.5961, "Focus Punch": 0.3518}},
  "Scizor": {"level": 82, "abilities": {"Swarm": 1}, "items": {"Leftovers": 0.9445, "Salac Berry": 0.0555}, "moves": {"Silver Wind": 0.6848, "Steel Wing": 0.6783, "Swords Dance": 0.6398, "Baton Pass": 0.4737, "Agility": 0.4254, "Hidden Power Ground": 0.385, "Hidden Power Rock": 0.3798, "Morning Sun": 0.3331}},
  "Scyther": {"level": 81, "abilities": {"Swarm": 1}, "items": {"Leftovers": 0.8148, "Choice Band": 0.1852}, "moves": {"Swords Dance": 0.8148, "Aerial Ace": 0.8031, "Silver Wind": 0.8026, "Baton Pass": 0.4883, "Hidden Power Ground": 0.4558, "Hidden Power Rock": 0.4502, "Quick Attack": 0.1852}},
  "Seaking": {"level": 90, "abilities": {"Swift Swim": 0.8151, "Water Veil": 0.1849}, "items": {"Leftovers": 0.7392, "Petaya Berry": 0.2608}, "moves": {"Hydro Pump": 1, "Rain Dance": 0.8096, "Ice Beam": 0.7425, "Megahorn": 0.7392, "Hidden Power Grass": 0.7086}},
  "Seviper": {"level": 89, "abilities": {"Shed Skin": 1}, "items": {"Leftovers": 1}, "moves": {"Sludge Bomb": 1, "Earthquake": 0.759, "Crunch": 0.75, "Hidden Power Grass": 0.7465, "Flamethrower": 0.7445}},
  "Sharpedo": {"level": 84, "abilities": {"Rough Skin": 1}, "items": {"Salac Berry": 0.6561, "Leftovers": 0.3094, "Choice Band": 0.0345}, "moves": {"Hydro Pump": 1, "Crunch": 0.6857, "Endure": 0.6561, "Earthquake": 0.4943, "Ice Beam": 0.4907, "Hidden Power Flying": 0.4635, "Return": 0.2097}},
  "Shedinja": {"level": 93, "abilities": {"Wonder Guard": 1}, "items": {"Lum Berry": 1}, "moves": {"Silver Wind": 0.8518, "Shadow Ball": 0.8472, "Hidden Power Ground": 0.8046, "Agility": 0.7991, "Baton Pass": 0.4964, "Toxic": 0.2009}},
  "Shiftry": {"level": 87, "abilities": {"Early Bird": 1}, "items": {"Salac Berry": 1}, "moves": {"Brick Break": 1, "Explosion": 1, "Shadow Ball": 1, "Swords Dance": 1}},
  "Shuckle": {"level": 97, "abilities": {"Sturdy": 1}, "items": {"Chesto Berry": 1}, "moves": {"Encore": 1, "Rest": 1, "Toxic": 1, "Wrap": 1}},
  "Skarmory": {"level": 80, "abilities": {"Keen Eye": 1}, "items": {"Leftovers": 0.7296, "Chesto Berry": 0.2704}, "moves": {"Drill Peck": 1, "Hidden Power Ground": 0.6729, "Toxic": 0.5708, "Rest": 0.5333, "Spikes": 0.4015, "Whirlwind": 0.3159, "Sleep Talk": 0.2628, "Protect": 0.2428}},
  "Slaking": {"level": 80, "abilities": {"Truant": 1}, "items": {"Choice Band": 1}, "moves": {"Earthquake": 1, "Focus Punch": 1, "Shadow Ball": 1, "Return": 0.8132, "Double-Edge": 0.1868}},
  "Slowbro": {"level": 82, "abilities": {"Own Tempo": 1}, "items": {"Leftovers": 0.8521, "Chesto Berry": 0.1479}, "moves": {"Surf": 0.9032, "Psychic": 0.8775, "Calm Mind": 0.6909, "Rest": 0.5029, "Sleep Talk": 0.355, "Fire Blast": 0.2873, "Ice Beam": 0.2785, "Thunder Wave": 0.1045}, "evs": {"atk": 0}, "ivs": {"atk": 0}},
  "Slowking": {"level": 84, "abilities": {"Own Tempo": 1}, "items": {"Leftovers": 0.8507, "Chesto Berry": 0.1493}, "moves": {"Psychic": 0.8819, "Surf": 0.8814, "Calm Mind": 0.6899, "Rest": 0.5209, "Sleep Talk": 0.3715, "Ice Beam": 0.274, "Flamethrower": 0.2727, "Thunder Wave": 0.1076}, "evs": {"atk": 0}, "ivs": {"atk": 0}},
  "Smeargle": {"level": 87, "abilities": {"Own Tempo": 1}, "items": {"Leftovers": 1}, "moves": {"Encore": 1, "Explosion": 1, "Spikes": 1, "Spore": 1}},
  "Sneasel": {"level": 87, "abilities": {"Inner Focus": 1}, "items": {"Leftovers": 0.935, "Choice Band": 0.065}, "moves": {"Swords Dance": 0.8962, "Substitute": 0.7653, "Hidden Power Flying": 0.7633, "Shadow Ball": 0.7576, "Brick Break": 0.7527, "Double-Edge": 0.065}},
  "Snorlax": {"level": 74, "abilities": {"Immunity": 1}, "items": {"Leftovers": 0.7976, "Choice Band": 0.1062, "Chesto Berry": 0.0962}, "moves": {"Curse": 0.742, "Return": 0.5674, "Shadow Ball": 0.5616, "Earthquake": 0.5587, "Body Slam": 0.4326, "Rest": 0.4173, "Self-Destruct": 0.3994, "Sleep Talk": 0.321}},
  "Solrock": {"level": 85, "abilities": {"Levitate": 1}, "items": {"Leftovers": 0.5909, "Choice Band": 0.4091}, "moves": {"Rock Slide": 1, "Earthquake": 0.6233, "Overheat": 0.6089, "Shadow Ball": 0.5958, "Reflect": 0.5909, "Explosion": 0.5811}},
  "Spinda": {"level": 94, "abilities": {"Own Tempo": 1}, "items": {"Leftovers": 1}, "moves": {"Body Slam": 1, "Substitute": 0.7506, "Shadow Ball": 0.5372, "Teeter Dance": 0.5248, "Encore": 0.5206, "Toxic": 0.386, "Focus Punch": 0.2808}},
  "Stantler": {"level": 84, "abilities": {"Intimidate": 1}, "items": {"Leftovers": 1}, "moves": {"Return": 1, "Shadow Ball": 0.759, "Hypnosis": 0.7569, "Earthquake": 0.7472, "Thunderbolt": 0.7369}},
  "Starmie": {"level": 77, "abilities": {"Natural Cure": 1}, "items": {"Leftovers": 1}, "moves": {"Psychic": 1, "Recover": 1, "Surf": 0.6129, "Ice Beam": 0.5107, "Thunderbolt": 0.4893, "Hydro Pump": 0.3871}, "evs": {"atk": 0}, "ivs": {"atk": 0}},
  "Steelix": {"level": 83, "abilities": {"Rock Head": 1}, "items": {"Chesto Berry": 0.6444, "Leftovers": 0.2688, "Choice Band": 0.0869}, "moves": {"Earthquake": 1, "Iron Tail": 0.7755, "Rest": 0.6444, "Hidden Power Rock": 0.6371, "Toxic": 0.4988, "Explosion": 0.2001, "Roar": 0.1813, "Double-Edge": 0.0628}},
  "Sudowoodo": {"level": 91, "abilities": {"Rock Head": 1}, "items": {"Leftovers": 0.631, "Choice Band": 0.369}, "moves": {"Rock Slide": 1, "Brick Break": 0.7118, "Explosion": 0.6917, "Earthquake": 0.6908, "Toxic": 0.631, "Double-Edge": 0.2748}},
  "Suicune": {"level": 76, "abilities": {"Pressure": 1}, "items": {"Leftovers": 0.8339, "Chesto Berry": 0.1661}, "moves": {"Surf": 1, "Ice Beam": 0.6678, "Rest": 0.6466, "Calm Mind": 0.604, "Sleep Talk": 0.4805, "Toxic": 0.314, "Substitute": 0.2871}, "evs": {"atk": 0}, "ivs": {"atk": 0}},
  "Sunflora": {"level": 94, "abilities": {"Chlorophyll": 1}, "items": {"Leftovers": 1}, "moves": {"Razor Leaf": 1, "Synthesis": 0.8048, "Toxic": 0.7399, "Leech Seed": 0.7287, "Hidden Power Fire": 0.7266}, "evs": {"atk": 0}},
  "Swalot": {"level": 89, "abilities": {"Sticky Hold": 0.6597, "Liquid Ooze": 0.3403}, "items": {"Leftovers": 0.9593, "Choice Band": 0.0407}, "moves": {"Sludge Bomb": 1, "Encore": 0.5562, "Ice Beam": 0.5529, "Hidden Power Ground": 0.5432, "Explosion": 0.5417, "Yawn": 0.5066, "Toxic": 0.2993}},
  "Swampert": {"level": 79, "abilities": {"Torrent": 1}, "items": {"Leftovers": 0.8349, "Chesto Berry": 0.1651}, "moves": {"Earthquake": 1, "Surf": 0.5925, "Rest": 0.4878, "Hydro Pump": 0.4075, "Ice Beam": 0.3856, "Rock Slide": 0.3726, "Toxic": 0.3331, "Sleep Talk": 0.3227, "Protect": 0.0982}},
  "Swellow": {"level": 81, "abilities": {"Guts": 1}, "items": {"Choice Band": 1}, "moves": {"Aerial Ace": 1, "Quick Attack": 1, "Return": 0.771, "Hidden Power Ground": 0.5059, "Hidden Power Fighting": 0.4941, "Double-Edge": 0.229}, "ivs": {"spa": 30, "spd": 30}},
  "Tangela": {"level": 91, "abilities": {"Chlorophyll": 1}, "items": {"Leftovers": 1}, "moves": {"Hidden Power Grass": 1, "Morning Sun": 0.7981, "Leech Seed": 0.7532, "Sleep Powder": 0.7262, "Stun Spore": 0.7225}, "evs": {"atk": 0}, "ivs": {"atk": 2, "spa": 30}},
  "Tauros": {"level": 77, "abilities": {"Intimidate": 1}, "items": {"Choice Band": 1}, "moves": {"Double-Edge": 1, "Earthquake": 1, "Return": 1, "Hidden Power Ghost": 0.5073, "Hidden Power Rock": 0.4927}, "ivs": {"def": 30, "spd": 30}},
  "Tentacruel": {"level": 83, "abilities": {"Clear Body": 0.6643, "Liquid Ooze": 0.3357}, "items": {"Leftovers": 1}, "moves": {"Ice Beam": 0.7139, "Haze": 0.7064, "Rapid Spin": 0.6836, "Toxic": 0.6045, "Surf": 0.5902, "Hydro Pump": 0.4098, "Giga Drain": 0.2915}},
  "Togetic": {"level": 92, "abilities": {"Serene Grace": 1}, "items": {"Leftovers": 1}, "moves": {"Seismic Toss": 1, "Soft-Boiled": 0.6359, "Charm": 0.4967, "Encore": 0.4807, "Toxic": 0.4741, "Thunder Wave": 0.4637, "Flamethrower": 0.4488}, "evs": {"atk": 0}, "ivs": {"atk": 0}},
  "Torkoal": {"level": 90, "abilities": {"White Smoke": 1}, "items": {"Chesto Berry": 0.7421, "Leftovers": 0.2579}, "moves": {"Hidden Power Grass": 1, "Rest": 0.7421, "Flamethrower": 0.7297, "Yawn": 0.6902, "Toxic": 0.304, "Fire Blast": 0.2703, "Explosion": 0.2638}, "ivs": {"spa": 30}},
  "Tropius": {"level": 93, "abilities": {"Chlorophyll": 1}, "items": {"Leftovers": 1}, "moves": {"Hidden Power Fire": 1, "Solar Beam": 1, "Sunny Day": 1, "Synthesis": 1}, "evs": {"atk": 0}, "ivs": {"atk": 2, "spa": 30, "spe": 30}},
  "Typhlosion": {"level": 79, "abilities": {"Blaze": 1}, "items": {"Petaya Berry": 0.6193, "Leftovers": 0.3807}, "moves": {"Substitute": 1, "Thunder Punch": 0.7246, "Fire Blast": 0.5382, "Flamethrower": 0.4618, "Hidden Power Ice": 0.4564, "Hidden Power Grass": 0.4382, "Focus Punch": 0.3807}},
  "Tyranitar": {"level": 75, "abilities": {"Sand Stream": 1}, "items": {"Leftovers": 0.5889, "Lum Berry": 0.3567, "Choice Band": 0.0544}, "moves": {"Rock Slide": 1, "Hidden Power Bug": 0.5061, "Earthquake": 0.5055, "Fire Blast": 0.4511, "Pursuit": 0.4295, "Substitute": 0.3848, "Dragon Dance": 0.3567, "Ice Beam": 0.2573, "Focus Punch": 0.1091}},
  "Umbreon": {"level": 85, "abilities": {"Synchronize": 1}, "items": {"Leftovers": 1}, "moves": {"Wish": 1, "Hidden Power Dark": 0.8136, "Protect": 0.7826, "Toxic": 0.7056, "Baton Pass": 0.6982}, "evs": {"atk": 0}},
  "Unown": {"level": 100, "abilities": {"Levitate": 1}, "items": {"Twisted Spoon": 1}, "moves": {"Hidden Power Psychic": 1}, "evs": {"atk": 0}, "ivs": {"atk": 2, "spe": 30}},
  "Ursaring": {"level": 81, "abilities": {"Guts": 1}, "items": {"Leftovers": 0.79, "Choice Band": 0.21}, "moves": {"Earthquake": 1, "Hidden Power Ghost": 1, "Return": 1, "Swords Dance": 0.79, "Focus Punch": 0.21}, "ivs": {"def": 30, "spd": 30}},
  "Vaporeon": {"level": 80, "abilities": {"Water Absorb": 1}, "items": {"Leftovers": 1}, "moves": {"Surf": 1, "Wish": 1, "Protect": 0.8155, "Ice Beam": 0.5978, "Toxic": 0.5866}, "evs": {"atk": 0}, "ivs": {"atk": 0}},
  "Venomoth": {"level": 88, "abilities": {"Shield Dust": 1}, "items": {"Leftovers": 1}, "moves": {"Substitute": 0.8016, "Sludge Bomb": 0.7417, "Signal Beam": 0.7269, "Sleep Powder": 0.6693, "Hidden Power Ground": 0.6636, "Baton Pass": 0.3969}},
  "Venusaur": {"level": 82, "abilities": {"Overgrow": 1}, "items": {"Leftovers": 0.9662, "Salac Berry": 0.0338}, "moves": {"Sludge Bomb": 1, "Synthesis": 0.7075, "Hidden Power Rock": 0.5449, "Earthquake": 0.5345, "Sleep Powder": 0.3736, "Curse": 0.3231, "Swords Dance": 0.3043, "Leech Seed": 0.212}},
  "Victreebel": {"level": 84, "abilities": {"Chlorophyll": 1}, "items": {"Leftovers": 1}, "moves": {"Sunny Day": 1, "Solar Beam": 0.7999, "Sludge Bomb": 0.793, "Hidden Power Fire": 0.7157, "Sleep Powder": 0.6914}},
  "Vigoroth": {"level": 86, "abilities": {"Vital Spirit": 1}, "items": {"Leftovers": 0.934, "Choice Band": 0.066}, "moves": {"Return": 1, "Bulk Up": 0.7069, "Slack Off": 0.692, "Earthquake": 0.5425, "Brick Break": 0.5401, "Shadow Ball": 0.5185}},
  "Vileplume": {"level": 85, "abilities": {"Chlorophyll": 1}, "items": {"Leftovers": 1}, "moves": {"Sludge Bomb": 0.9058, "Synthesis": 0.7101, "Hidden Power Fire": 0.6273, "Sleep Powder": 0.5867, "Aromatherapy": 0.5367, "Solar Beam": 0.3179, "Sunny Day": 0.3155}},
  "Volbeat": {"level": 93, "abilities": {"Swarm": 1}, "items": {"Leftovers": 1}, "moves": {"Baton Pass": 1, "Ice Punch": 1, "Tail Glow": 1, "Thunderbolt": 1}, "evs": {"atk": 0}, "ivs": {"atk": 0}},
  "Wailord": {"level": 87, "abilities": {"Water Veil": 1}, "items": {"Leftovers": 0.9036, "Chesto Berry": 0.0964}, "moves": {"Surf": 1, "Rest": 0.5718, "Ice Beam": 0.5701, "Hidden Power Grass": 0.5509, "Toxic": 0.5338, "Sleep Talk": 0.4755, "Self-Destruct": 0.298}},
  "Walrein": {"level": 81, "abilities": {"Thick Fat": 1}, "items": {"Leftovers": 0.877, "Chesto Berry": 0.123}, "moves": {"Surf": 1, "Ice Beam": 0.7611, "Rest": 0.5536, "Toxic": 0.4425, "Hidden Power Grass": 0.4389, "Sleep Talk": 0.4306, "Encore": 0.3733}, "evs": {"atk": 0}},
  "Weezing": {"level": 82, "abilities": {"Levitate": 1}, "items": {"Leftovers": 1}, "moves": {"Sludge Bomb": 1, "Fire Blast": 0.5666, "Haze": 0.5498, "Pain Split": 0.5481, "Explosion": 0.5467, "Toxic": 0.4978, "Will-O-Wisp": 0.291}},
  "Whiscash": {"level": 86, "abilities": {"Oblivious": 1}, "items": {"Leftovers": 0.8289, "Chesto Berry": 0.1259, "Choice Band": 0.0452}, "moves": {"Earthquake": 1, "Surf": 1, "Rest": 0.4921, "Sleep Talk": 0.3662, "Toxic": 0.2368, "Rock Slide": 0.2326, "Hidden Power Bug": 0.2252, "Ice Beam": 0.224, "Spark": 0.223}},
  "Wigglytuff": {"level": 90, "abilities": {"Cute Charm": 1}, "items": {"Leftovers": 1}, "moves": {"Return": 1, "Wish": 0.8237, "Protect": 0.5306, "Thunderbolt": 0.4388, "Fire Blast": 0.4183, "Ice Beam": 0.4151, "Toxic": 0.3736}},
  "Wobbuffet": {"level": 81, "abilities": {"Shadow Tag": 1}, "items": {"Leftovers": 1}, "moves": {"Counter": 1, "Destiny Bond": 1, "Encore": 1, "Mirror Coat": 1}, "evs": {"atk": 0}, "ivs": {"atk": 0}},
  "Xatu": {"level": 84, "abilities": {"Synchronize": 0.6546, "Early Bird": 0.3454}, "items": {"Leftovers": 1}, "moves": {"Psychic": 1, "Wish": 0.8456, "Baton Pass": 0.7, "Calm Mind": 0.6114, "Hidden Power Fire": 0.5518, "Reflect": 0.2911}, "evs": {"atk": 0}},
  "Yanma": {"level": 90, "abilities": {"Speed Boost": 1}, "items": {"Liechi Berry": 0.6157, "Leftovers": 0.3843}, "moves": {"Hidden Power Flying": 1, "Substitute": 1, "Shadow Ball": 0.834, "Reversal": 0.6157, "Hypnosis": 0.5503}, "ivs": {"hp": 30, "atk": 30, "def": 30, "spa": 30, "spd": 30}},
  "Zangoose": {"level": 80, "abilities": {"Immunity": 1}, "items": {"Leftovers": 0.6061, "Salac Berry": 0.2017, "Choice Band": 0.1921}, "moves": {"Return": 1, "Swords Dance": 0.8079, "Quick Attack": 0.7983, "Brick Break": 0.6983, "Shadow Ball": 0.6956}},
  "Zapdos": {"level": 76, "abilities": {"Pressure": 1}, "items": {"Leftovers": 1}, "moves": {"Thunderbolt": 1, "Substitute": 0.742, "Baton Pass": 0.6467, "Hidden Power Ice": 0.5927, "Toxic": 0.4276, "Thunder Wave": 0.4008, "Agility": 0.1902}, "evs": {"atk": 0}}
}